{
  "answer_isolation": {
    "answer_payload_present": false,
    "answer_reference_disclosed": false,
    "status": "PROGRAMMATICALLY_SCANNED"
  },
  "bazi": {
    "calendar": {
      "gender": "女",
      "lunar": "丙寅年六月十七日寅时",
      "solar": "1986-7-23 4:18",
      "true_solar": "1986-7-23 4:11"
    },
    "hidden_stems_ten_gods": {
      "day": [
        "戊 比肩",
        "乙 正官",
        "癸 正财"
      ],
      "hour": [
        "甲 七杀",
        "丙 偏印",
        "戊 比肩"
      ],
      "month": [
        "己 劫财",
        "丁 正印",
        "乙 正官"
      ],
      "year": [
        "甲 七杀",
        "丙 偏印",
        "戊 比肩"
      ]
    },
    "luck": {
      "cycles": [
        {
          "nominal_age": 6,
          "pillar": "甲午",
          "start_year": 1991
        },
        {
          "nominal_age": 16,
          "pillar": "癸巳",
          "start_year": 2001
        },
        {
          "nominal_age": 26,
          "pillar": "壬辰",
          "start_year": 2011
        },
        {
          "nominal_age": 36,
          "pillar": "辛卯",
          "start_year": 2021
        },
        {
          "nominal_age": 46,
          "pillar": "庚寅",
          "start_year": 2031
        },
        {
          "nominal_age": 56,
          "pillar": "己丑",
          "start_year": 2041
        },
        {
          "nominal_age": 66,
          "pillar": "戊子",
          "start_year": 2051
        },
        {
          "nominal_age": 76,
          "pillar": "丁亥",
          "start_year": 2061
        },
        {
          "nominal_age": 86,
          "pillar": "丙戌",
          "start_year": 2071
        }
      ],
      "direction": "REVERSE",
      "first_major_luck_nominal_age": 6,
      "first_major_luck_year": 1991,
      "ocr_year_candidates": [
        1986,
        1991,
        2001,
        2011,
        2021,
        2031,
        2041,
        2051,
        2061,
        2071,
        2021,
        2022,
        2023,
        2024,
        2025,
        2026,
        2027,
        2028,
        2029,
        2030
      ]
    },
    "pillars": {
      "day": "戊辰",
      "hour": "甲寅",
      "month": "乙未",
      "year": "丙寅"
    },
    "source_image": {
      "bytes": 380813,
      "height": 1278,
      "path": "case-bank/raw/CASE-057/bazi.png",
      "sha256": "d9882f313f8ba35967af0f9e4df01edad102a3a517a554768f01c9065ba1dcc5",
      "width": 1180
    },
    "transcription_status": "DERIVED_FROM_ZIWEI_TEXT_AND_IMAGE_YEAR_BOUNDARY"
  },
  "binding": {
    "source_manifest": "sources/canonical-manifest.json",
    "training_policy": "config/training-policy.json"
  },
  "case_id": "CASE-057",
  "dataset_split": "DEVELOPMENT",
  "identity_group_id": "PERSON-F483F8092534B345",
  "input": {
    "body_lord": "天梁",
    "body_palace_branch": "酉",
    "clock_time": "1986-7-23 4:18",
    "five_element_bureau": "水二局",
    "gender": "女",
    "life_lord": "禄存",
    "longitude": "120.000",
    "lunar_time": "丙寅年六月十七日寅时",
    "non_solar_term_pillars": "丙寅 乙未 戊辰 甲寅",
    "pillars": {
      "day": "戊辰",
      "hour": "甲寅",
      "month": "乙未",
      "year": "丙寅"
    },
    "solar_term_pillars": "丙寅 乙未 戊辰 甲寅",
    "true_solar_time": "1986-7-23 4:11",
    "year_doujun": "酉"
  },
  "legacy_case_id": null,
  "quality": {
    "issues": [],
    "status": "ACCEPTED"
  },
  "questions": {
    "parsed": [
      {
        "options": [
          {
            "option_id": "A",
            "text": "1 个"
          },
          {
            "option_id": "B",
            "text": "2 个"
          },
          {
            "option_id": "C",
            "text": "没有"
          },
          {
            "option_id": "D",
            "text": "流产了多次"
          }
        ],
        "preblind_profile": {
          "atomization_required": false,
          "endpoint_tags": [
            "FAMILY_COMPOSITION",
            "CHILDBIRTH"
          ],
          "governance_tags": [],
          "option_atom_hints": {
            "A": [
              "1 个"
            ],
            "B": [
              "2 个"
            ],
            "C": [
              "没有"
            ],
            "D": [
              "流产了多次"
            ]
          },
          "reasoning_skill_tags": [
            "TOPIC_PALACE_ROUTING",
            "NATAL_STRUCTURE",
            "EVIDENCE_WEIGHTING",
            "COUNTEREVIDENCE_REVERSAL",
            "ZIWEI_BAZI_ARBITRATION",
            "OPTION_GRANULARITY",
            "STATIC_DYNAMIC_LAYERING",
            "PALACE_TRANSFORMATION_CHAIN",
            "BAZI_STRUCTURE_THEN_TRIGGER",
            "UNCERTAINTY_CALIBRATION",
            "SUBJECT_ENTITY_ROUTING",
            "CAUSAL_ACTOR_DIRECTION",
            "TIME_LAYER_ACTIVATION",
            "EVENT_ENDPOINT_CLOSURE"
          ],
          "source_routes": [
            "S00",
            "S01",
            "S03",
            "S04",
            "S08",
            "S09",
            "S10",
            "S11",
            "S14",
            "S15",
            "S16",
            "S17",
            "S18",
            "S19"
          ],
          "subject_tags": [
            "CHILDREN"
          ],
          "time_scope_tags": [
            "SPECIFIC_YEAR",
            "CURRENT_STATUS"
          ],
          "topic_tags": [
            "CHILDREN_FERTILITY",
            "MAJOR_YEAR_EVENT"
          ]
        },
        "question_id": "Q1",
        "source_question_number": "1",
        "stem": "截至2019年，命主有几个子女?"
      },
      {
        "options": [
          {
            "option_id": "A",
            "text": "有做(有下属)"
          },
          {
            "option_id": "B",
            "text": "自顾 (个体户)"
          },
          {
            "option_id": "C",
            "text": "同人合作"
          },
          {
            "option_id": "D",
            "text": "家庭主妇"
          }
        ],
        "preblind_profile": {
          "atomization_required": false,
          "endpoint_tags": [
            "BUSINESS_OUTCOME"
          ],
          "governance_tags": [],
          "option_atom_hints": {
            "A": [
              "有做(有下属)"
            ],
            "B": [
              "自顾 (个体户)"
            ],
            "C": [
              "同人合作"
            ],
            "D": [
              "家庭主妇"
            ]
          },
          "reasoning_skill_tags": [
            "TOPIC_PALACE_ROUTING",
            "NATAL_STRUCTURE",
            "EVIDENCE_WEIGHTING",
            "COUNTEREVIDENCE_REVERSAL",
            "ZIWEI_BAZI_ARBITRATION",
            "OPTION_GRANULARITY",
            "STATIC_DYNAMIC_LAYERING",
            "PALACE_TRANSFORMATION_CHAIN",
            "BAZI_STRUCTURE_THEN_TRIGGER",
            "UNCERTAINTY_CALIBRATION",
            "TIME_LAYER_ACTIVATION",
            "EVENT_ENDPOINT_CLOSURE",
            "REALITY_SCALE_MAPPING",
            "REGION_ERA_NORMALIZATION",
            "CAREER_PROFILE_CLOSURE"
          ],
          "source_routes": [
            "S00",
            "S01",
            "S02",
            "S03",
            "S04",
            "S08",
            "S09",
            "S10",
            "S11",
            "S14",
            "S15",
            "S16",
            "S17",
            "S18",
            "S19"
          ],
          "subject_tags": [
            "SELF"
          ],
          "time_scope_tags": [
            "SPECIFIC_YEAR"
          ],
          "topic_tags": [
            "CAREER_EDUCATION",
            "BUSINESS_PARTNERSHIP",
            "MAJOR_YEAR_EVENT"
          ]
        },
        "question_id": "Q2",
        "source_question_number": "2",
        "stem": "2019年时，命主是否有做生意，何种形式?"
      },
      {
        "options": [
          {
            "option_id": "A",
            "text": "自己买"
          },
          {
            "option_id": "B",
            "text": "租地方"
          },
          {
            "option_id": "C",
            "text": "公屋"
          },
          {
            "option_id": "D",
            "text": "长住酒店"
          }
        ],
        "preblind_profile": {
          "atomization_required": false,
          "endpoint_tags": [
            "OTHER"
          ],
          "governance_tags": [],
          "option_atom_hints": {
            "A": [
              "自己买"
            ],
            "B": [
              "租地方"
            ],
            "C": [
              "公屋"
            ],
            "D": [
              "长住酒店"
            ]
          },
          "reasoning_skill_tags": [
            "TOPIC_PALACE_ROUTING",
            "NATAL_STRUCTURE",
            "EVIDENCE_WEIGHTING",
            "COUNTEREVIDENCE_REVERSAL",
            "ZIWEI_BAZI_ARBITRATION",
            "OPTION_GRANULARITY",
            "STATIC_DYNAMIC_LAYERING",
            "PALACE_TRANSFORMATION_CHAIN",
            "BAZI_STRUCTURE_THEN_TRIGGER",
            "UNCERTAINTY_CALIBRATION",
            "TIME_LAYER_ACTIVATION",
            "EVENT_ENDPOINT_CLOSURE"
          ],
          "source_routes": [
            "S00",
            "S01",
            "S03",
            "S04",
            "S08",
            "S09",
            "S10",
            "S11",
            "S14",
            "S15",
            "S16",
            "S17",
            "S18",
            "S19"
          ],
          "subject_tags": [
            "SELF"
          ],
          "time_scope_tags": [
            "MULTI_YEAR_PERIOD"
          ],
          "topic_tags": [
            "OTHER"
          ]
        },
        "question_id": "Q3",
        "source_question_number": "3",
        "stem": "命主在 22 岁---31 岁大运中，住宅情况如何?"
      },
      {
        "options": [
          {
            "option_id": "A",
            "text": "没有"
          },
          {
            "option_id": "B",
            "text": "已离婚"
          },
          {
            "option_id": "C",
            "text": "分房睡"
          },
          {
            "option_id": "D",
            "text": "分开住"
          }
        ],
        "preblind_profile": {
          "atomization_required": false,
          "endpoint_tags": [
            "RELATIONSHIP_STATUS",
            "DIVORCE"
          ],
          "governance_tags": [],
          "option_atom_hints": {
            "A": [
              "没有"
            ],
            "B": [
              "已离婚"
            ],
            "C": [
              "分房睡"
            ],
            "D": [
              "分开住"
            ]
          },
          "reasoning_skill_tags": [
            "TOPIC_PALACE_ROUTING",
            "NATAL_STRUCTURE",
            "EVIDENCE_WEIGHTING",
            "COUNTEREVIDENCE_REVERSAL",
            "ZIWEI_BAZI_ARBITRATION",
            "OPTION_GRANULARITY",
            "STATIC_DYNAMIC_LAYERING",
            "PALACE_TRANSFORMATION_CHAIN",
            "BAZI_STRUCTURE_THEN_TRIGGER",
            "UNCERTAINTY_CALIBRATION",
            "TIME_LAYER_ACTIVATION",
            "EVENT_ENDPOINT_CLOSURE",
            "RELATIONSHIP_SEQUENCE"
          ],
          "source_routes": [
            "S00",
            "S01",
            "S03",
            "S04",
            "S08",
            "S09",
            "S10",
            "S11",
            "S14",
            "S15",
            "S16",
            "S17",
            "S18",
            "S19"
          ],
          "subject_tags": [
            "SELF"
          ],
          "time_scope_tags": [
            "SPECIFIC_YEAR"
          ],
          "topic_tags": [
            "MARRIAGE_RELATIONSHIP",
            "MAJOR_YEAR_EVENT"
          ]
        },
        "question_id": "Q4",
        "source_question_number": "4",
        "stem": "命主在 32 岁至2019年间有离婚吗?"
      },
      {
        "options": [
          {
            "option_id": "A",
            "text": "和顺"
          },
          {
            "option_id": "B",
            "text": "自立型"
          },
          {
            "option_id": "C",
            "text": "强势"
          },
          {
            "option_id": "D",
            "text": "无自主见依赖人"
          }
        ],
        "preblind_profile": {
          "atomization_required": false,
          "endpoint_tags": [
            "PERSONALITY"
          ],
          "governance_tags": [],
          "option_atom_hints": {
            "A": [
              "和顺"
            ],
            "B": [
              "自立型"
            ],
            "C": [
              "强势"
            ],
            "D": [
              "无自主见依赖人"
            ]
          },
          "reasoning_skill_tags": [
            "TOPIC_PALACE_ROUTING",
            "NATAL_STRUCTURE",
            "EVIDENCE_WEIGHTING",
            "COUNTEREVIDENCE_REVERSAL",
            "ZIWEI_BAZI_ARBITRATION",
            "OPTION_GRANULARITY",
            "STATIC_DYNAMIC_LAYERING",
            "PALACE_TRANSFORMATION_CHAIN",
            "BAZI_STRUCTURE_THEN_TRIGGER",
            "UNCERTAINTY_CALIBRATION"
          ],
          "source_routes": [
            "S00",
            "S01",
            "S03",
            "S04",
            "S05",
            "S06",
            "S07",
            "S08",
            "S09",
            "S11",
            "S12",
            "S13",
            "S16",
            "S17",
            "S18",
            "S19"
          ],
          "subject_tags": [
            "SELF"
          ],
          "time_scope_tags": [
            "OTHER"
          ],
          "topic_tags": [
            "PERSONALITY_APPEARANCE"
          ]
        },
        "question_id": "Q5",
        "source_question_number": "5",
        "stem": "命主的性格属于哪种类型?"
      }
    ],
    "question_count": 5,
    "source_path": "case-bank/raw/CASE-057/questions.txt",
    "source_sha256": "0902cc89a6048f9284ba44ca6b4898745ba8c957d38713b9a73add514bc065fb"
  },
  "schema": "FORTUNE-CASE-BANK-CASE-V1",
  "source_label": "例题57",
  "ziwei": {
    "sha256": "b047e9f323816b41e013501c4d68e976f3c8cc040f6ce2f6bdf64b17feb55945",
    "source_path": "case-bank/raw/CASE-057/ziwei.txt",
    "text": "├符号定义\n│ ├(↓:离心自化)\n│ ├(↑:向心自化，从对宫化入)\n│ ├(┏ : 生日前小限)\n│ └( ┓: 生日后小限)\n│\n├基本信息\n│ │\n│ ├性别 : 女\n│ ├地理经度 : 120.000\n│ ├钟表时间 : 1986-7-23 4:18\n│ ├真太阳时 : 1986-7-23 4:11\n│ ├农历时间 : 丙寅年六月十七日寅时\n│ ├节气四柱 : 丙寅 乙未 戊辰 甲寅\n│ ├非节气四柱 : 丙寅 乙未 戊辰 甲寅\n│ ├五行局数 : 水二局\n│ └身主:天梁; 命主:禄存; 子年斗君:酉; 身宫:酉\n│\n├命盘十二宫\n│ │ \n│ ├疾厄宫[庚子]\n│ │ ├主星 : 天梁[庙]\n│ │ ├辅星 : 无\n│ │ ├小星 : 天福[平],天伤[陷],解神[庙],天厨\n│ │ ├神煞\n│ │ │ ├岁前星 : 吊客\n│ │ │ ├将前星 : 灾煞\n│ │ │ ├十二长生 : 墓\n│ │ │ └太岁煞禄 : 奏书\n│ │ ├大限 : 52 ~ 61虚岁\n│ │ ├小限 : 5,17,29,41,53虚岁\n│ │ ├流年 : 11,23,35,47,59虚岁\n│ │ └限流叠宫 : 无\n│ │ \n│ ├财帛宫[辛丑]\n│ │ ├主星 : 廉贞[利][生年忌],七杀[庙]\n│ │ ├辅星 : 地劫[陷]\n│ │ ├小星 : 红鸾[陷],三台[庙],八座[庙],寡宿[平]\n│ │ ├神煞\n│ │ │ ├岁前星 : 病符\n│ │ │ ├将前星 : 天煞\n│ │ │ ├十二长生 : 死\n│ │ │ └太岁煞禄 : 将军\n│ │ ├大限 : 42 ~ 51虚岁\n│ │ ├小限 : 4,16,28,40,52虚岁\n│ │ ├流年 : 12,24,36,48,60虚岁\n│ │ └限流叠宫 : 无\n│ │ \n│ ├子女宫[庚寅]\n│ │ ├主星 : 无\n│ │ ├辅星 : 无\n│ │ ├小星 : 天刑[庙]\n│ │ ├神煞\n│ │ │ ├岁前星 : 岁建\n│ │ │ ├将前星 : 指背\n│ │ │ ├十二长生 : 病\n│ │ │ └太岁煞禄 : 小耗\n│ │ ├大限 : 32 ~ 41虚岁\n│ │ ├小限 : 3,15,27,39,51虚岁\n│ │ ├流年 : 1,13,25,37,49虚岁\n│ │ └限流叠宫 : 无\n│ │ \n│ ├夫妻宫[辛卯]\n│ │ ├主星 : 无\n│ │ ├辅星 : 火星[利]\n│ │ ├小星 : 天月,天空[平],咸池[平]\n│ │ ├神煞\n│ │ │ ├岁前星 : 晦气\n│ │ │ ├将前星 : 咸池\n│ │ │ ├十二长生 : 衰\n│ │ │ └太岁煞禄 : 青龙\n│ │ ├大限 : 22 ~ 31虚岁\n│ │ ├小限 : 2,14,26,38,50虚岁\n│ │ ├流年 : 2,14,26,38,50虚岁\n│ │ └限流叠宫 : 无\n│ │ \n│ ├兄弟宫[壬辰]\n│ │ ├主星 : 天同[平][生年禄]\n│ │ ├辅星 : 陀罗[庙]\n│ │ ├小星 : 封诰,截空[陷],天哭[平],阴煞\n│ │ ├神煞\n│ │ │ ├岁前星 : 丧门\n│ │ │ ├将前星 : 月煞\n│ │ │ ├十二长生 : 帝旺\n│ │ │ └太岁煞禄 : 力士\n│ │ ├大限 : 12 ~ 21虚岁\n│ │ ├小限 : 1,13,25,37,49虚岁\n│ │ ├流年 : 3,15,27,39,51虚岁\n│ │ └限流叠宫 : 无\n│ │ \n│ ├命  宫[癸巳]\n│ │ ├主星 : 武曲[平][↑禄],破军[平][↓禄]\n│ │ ├辅星 : 右弼[平],禄存[庙],铃星[得]\n│ │ ├小星 : 天官[旺],副截[庙],孤辰[陷]\n│ │ ├神煞\n│ │ │ ├岁前星 : 贯索\n│ │ │ ├将前星 : 亡神\n│ │ │ ├十二长生 : 临官\n│ │ │ └太岁煞禄 : 博士\n│ │ ├大限 : 2 ~ 11虚岁\n│ │ ├小限 : 12,24,36,48,60虚岁\n│ │ ├流年 : 4,16,28,40,52虚岁\n│ │ └限流叠宫 : 无\n│ │ \n│ ├父母宫[甲午]\n│ │ ├主星 : 太阳[旺][↓忌][↑禄]\n│ │ ├辅星 : 文曲[陷],擎羊[陷]\n│ │ ├小星 : 天姚[平],龙池[不]\n│ │ ├神煞\n│ │ │ ├岁前星 : 官符\n│ │ │ ├将前星 : 將星\n│ │ │ ├十二长生 : 冠带\n│ │ │ └太岁煞禄 : 官符\n│ │ ├大限 : 112 ~ 121虚岁\n│ │ ├小限 : 11,23,35,47,59虚岁\n│ │ ├流年 : 5,17,29,41,53虚岁\n│ │ └限流叠宫 : 无\n│ │ \n│ ├福德宫[乙未]\n│ │ ├主星 : 天府[庙]\n│ │ ├辅星 : 无\n│ │ ├小星 : 天喜[陷],天才[平],月德\n│ │ ├神煞\n│ │ │ ├岁前星 : 小耗\n│ │ │ ├将前星 : 攀鞍\n│ │ │ ├十二长生 : 沐浴\n│ │ │ └太岁煞禄 : 伏兵\n│ │ ├大限 : 102 ~ 111虚岁\n│ │ ├小限 : 10,22,34,46,58虚岁\n│ │ ├流年 : 6,18,30,42,54虚岁\n│ │ └限流叠宫 : 无\n│ │ \n│ ├田宅宫[丙申][来因]\n│ │ ├主星 : 天机[得][生年权][↓权],太阴[利][↑科]\n│ │ ├辅星 : 文昌[得][生年科][↓科],天马[旺]\n│ │ ├小星 : 凤阁[不],台辅,天巫,天虚[庙],年解[利]\n│ │ ├神煞\n│ │ │ ├岁前星 : 岁破\n│ │ │ ├将前星 : 岁驿\n│ │ │ ├十二长生 : 长生\n│ │ │ └太岁煞禄 : 大耗\n│ │ ├大限 : 92 ~ 101虚岁\n│ │ ├小限 : 9,21,33,45,57虚岁\n│ │ ├流年 : 7,19,31,43,55虚岁\n│ │ └限流叠宫 : 无\n│ │ \n│ ├官禄宫[丁酉][身宫]\n│ │ ├主星 : 紫微[旺],贪狼[利]\n│ │ ├辅星 : 左辅[陷],天钺[庙],地空[庙]\n│ │ ├小星 : 天贵[庙],破碎[平],大耗[不],龙德\n│ │ ├神煞\n│ │ │ ├岁前星 : 龙德\n│ │ │ ├将前星 : 息神\n│ │ │ ├十二长生 : 养\n│ │ │ └太岁煞禄 : 病符\n│ │ ├大限 : 82 ~ 91虚岁\n│ │ ├小限 : 8,20,32,44,56虚岁\n│ │ ├流年 : 8,20,32,44,56虚岁\n│ │ └限流叠宫 : 无\n│ │ \n│ ├交友宫[戊戌]\n│ │ ├主星 : 巨门[陷]\n│ │ ├辅星 : 无\n│ │ ├小星 : 天使[陷],旬空[陷],蜚廉,华盖[平]\n│ │ ├神煞\n│ │ │ ├岁前星 : 白虎\n│ │ │ ├将前星 : 华盖\n│ │ │ ├十二长生 : 胎\n│ │ │ └太岁煞禄 : 喜神\n│ │ ├大限 : 72 ~ 81虚岁\n│ │ ├小限 : 7,19,31,43,55虚岁\n│ │ ├流年 : 9,21,33,45,57虚岁\n│ │ └限流叠宫 : 无\n│ │ \n│ └迁移宫[己亥]\n│ │ ├主星 : 天相[得]\n│ │ ├辅星 : 天魁[旺]\n│ │ ├小星 : 恩光[不],天寿[旺],副旬[平],劫煞,天德[平]\n│ │ ├神煞\n│ │ │ ├岁前星 : 天德\n│ │ │ ├将前星 : 劫煞\n│ │ │ ├十二长生 : 绝\n│ │ │ └太岁煞禄 : 飞廉\n│ │ ├大限 : 62 ~ 71虚岁\n│ │ ├小限 : 6,18,30,42,54虚岁\n│ │ ├流年 : 10,22,34,46,58虚岁\n│ │ └限流叠宫 : 无\n│\n├大限流年信息\n│ │\n│ ├第1大限[癸巳]\n│ │ ├起止年份:1987年(2虚岁)~1996年(11虚岁)\n│ │ ├大限四化:破军禄,巨门权,太阴科,贪狼忌\n│ │ ├流年\n│ │ │ ├1987年[丁卯](2虚岁)\n│ │ │ │ ├命宫干支:辛卯\n│ │ │ │ └流年四化:太阴禄,天同权,天机科,巨门忌\n│ │ │ ├1988年[戊辰](3虚岁)\n│ │ │ │ ├命宫干支:壬辰\n│ │ │ │ └流年四化:贪狼禄,太阴权,右弼科,天机忌\n│ │ │ ├1989年[己巳](4虚岁)\n│ │ │ │ ├命宫干支:癸巳\n│ │ │ │ └流年四化:武曲禄,贪狼权,天梁科,文曲忌\n│ │ │ ├1990年[庚午](5虚岁)\n│ │ │ │ ├命宫干支:甲午\n│ │ │ │ └流年四化:太阳禄,武曲权,太阴科,天同忌\n│ │ │ ├1991年[辛未](6虚岁)\n│ │ │ │ ├命宫干支:乙未\n│ │ │ │ └流年四化:巨门禄,太阳权,文曲科,文昌忌\n│ │ │ ├1992年[壬申](7虚岁)\n│ │ │ │ ├命宫干支:丙申\n│ │ │ │ └流年四化:天梁禄,紫微权,左辅科,武曲忌\n│ │ │ ├1993年[癸酉](8虚岁)\n│ │ │ │ ├命宫干支:丁酉\n│ │ │ │ └流年四化:破军禄,巨门权,太阴科,贪狼忌\n│ │ │ ├1994年[甲戌](9虚岁)\n│ │ │ │ ├命宫干支:戊戌\n│ │ │ │ └流年四化:廉贞禄,破军权,武曲科,太阳忌\n│ │ │ ├1995年[乙亥](10虚岁)\n│ │ │ │ ├命宫干支:己亥\n│ │ │ │ └流年四化:天机禄,天梁权,紫微科,太阴忌\n│ │ │ ├1996年[丙子](11虚岁)\n│ │ │ │ ├命宫干支:庚子\n│ │ └ └ └流年四化:天同禄,天机权,文昌科,廉贞忌\n│ │\n│ ├第2大限[壬辰]\n│ │ ├起止年份:1997年(12虚岁)~2006年(21虚岁)\n│ │ ├大限四化:天梁禄,紫微权,左辅科,武曲忌\n│ │ ├流年\n│ │ │ ├1997年[丁丑](12虚岁)\n│ │ │ │ ├命宫干支:辛丑\n│ │ │ │ └流年四化:太阴禄,天同权,天机科,巨门忌\n│ │ │ ├1998年[戊寅](13虚岁)\n│ │ │ │ ├命宫干支:庚寅\n│ │ │ │ └流年四化:贪狼禄,太阴权,右弼科,天机忌\n│ │ │ ├1999年[己卯](14虚岁)\n│ │ │ │ ├命宫干支:辛卯\n│ │ │ │ └流年四化:武曲禄,贪狼权,天梁科,文曲忌\n│ │ │ ├2000年[庚辰](15虚岁)\n│ │ │ │ ├命宫干支:壬辰\n│ │ │ │ └流年四化:太阳禄,武曲权,太阴科,天同忌\n│ │ │ ├2001年[辛巳](16虚岁)\n│ │ │ │ ├命宫干支:癸巳\n│ │ │ │ └流年四化:巨门禄,太阳权,文曲科,文昌忌\n│ │ │ ├2002年[壬午](17虚岁)\n│ │ │ │ ├命宫干支:甲午\n│ │ │ │ └流年四化:天梁禄,紫微权,左辅科,武曲忌\n│ │ │ ├2003年[癸未](18虚岁)\n│ │ │ │ ├命宫干支:乙未\n│ │ │ │ └流年四化:破军禄,巨门权,太阴科,贪狼忌\n│ │ │ ├2004年[甲申](19虚岁)\n│ │ │ │ ├命宫干支:丙申\n│ │ │ │ └流年四化:廉贞禄,破军权,武曲科,太阳忌\n│ │ │ ├2005年[乙酉](20虚岁)\n│ │ │ │ ├命宫干支:丁酉\n│ │ │ │ └流年四化:天机禄,天梁权,紫微科,太阴忌\n│ │ │ ├2006年[丙戌](21虚岁)\n│ │ │ │ ├命宫干支:戊戌\n│ │ └ └ └流年四化:天同禄,天机权,文昌科,廉贞忌\n│ │\n│ ├第3大限[辛卯]\n│ │ ├起止年份:2007年(22虚岁)~2016年(31虚岁)\n│ │ ├大限四化:巨门禄,太阳权,文曲科,文昌忌\n│ │ ├流年\n│ │ │ ├2007年[丁亥](22虚岁)\n│ │ │ │ ├命宫干支:己亥\n│ │ │ │ └流年四化:太阴禄,天同权,天机科,巨门忌\n│ │ │ ├2008年[戊子](23虚岁)\n│ │ │ │ ├命宫干支:庚子\n│ │ │ │ └流年四化:贪狼禄,太阴权,右弼科,天机忌\n│ │ │ ├2009年[己丑](24虚岁)\n│ │ │ │ ├命宫干支:辛丑\n│ │ │ │ └流年四化:武曲禄,贪狼权,天梁科,文曲忌\n│ │ │ ├2010年[庚寅](25虚岁)\n│ │ │ │ ├命宫干支:庚寅\n│ │ │ │ └流年四化:太阳禄,武曲权,太阴科,天同忌\n│ │ │ ├2011年[辛卯](26虚岁)\n│ │ │ │ ├命宫干支:辛卯\n│ │ │ │ └流年四化:巨门禄,太阳权,文曲科,文昌忌\n│ │ │ ├2012年[壬辰](27虚岁)\n│ │ │ │ ├命宫干支:壬辰\n│ │ │ │ └流年四化:天梁禄,紫微权,左辅科,武曲忌\n│ │ │ ├2013年[癸巳](28虚岁)\n│ │ │ │ ├命宫干支:癸巳\n│ │ │ │ └流年四化:破军禄,巨门权,太阴科,贪狼忌\n│ │ │ ├2014年[甲午](29虚岁)\n│ │ │ │ ├命宫干支:甲午\n│ │ │ │ └流年四化:廉贞禄,破军权,武曲科,太阳忌\n│ │ │ ├2015年[乙未](30虚岁)\n│ │ │ │ ├命宫干支:乙未\n│ │ │ │ └流年四化:天机禄,天梁权,紫微科,太阴忌\n│ │ │ ├2016年[丙申](31虚岁)\n│ │ │ │ ├命宫干支:丙申\n│ │ └ └ └流年四化:天同禄,天机权,文昌科,廉贞忌\n│ │\n│ ├第4大限[庚寅]\n│ │ ├起止年份:2017年(32虚岁)~2026年(41虚岁)\n│ │ ├大限四化:太阳禄,武曲权,太阴科,天同忌\n│ │ ├流年\n│ │ │ ├2017年[丁酉](32虚岁)\n│ │ │ │ ├命宫干支:丁酉\n│ │ │ │ └流年四化:太阴禄,天同权,天机科,巨门忌\n│ │ │ ├2018年[戊戌](33虚岁)\n│ │ │ │ ├命宫干支:戊戌\n│ │ │ │ └流年四化:贪狼禄,太阴权,右弼科,天机忌\n│ │ │ ├2019年[己亥](34虚岁)\n│ │ │ │ ├命宫干支:己亥\n│ │ │ │ └流年四化:武曲禄,贪狼权,天梁科,文曲忌\n│ │ │ ├2020年[庚子](35虚岁)\n│ │ │ │ ├命宫干支:庚子\n│ │ │ │ └流年四化:太阳禄,武曲权,太阴科,天同忌\n│ │ │ ├2021年[辛丑](36虚岁)\n│ │ │ │ ├命宫干支:辛丑\n│ │ │ │ └流年四化:巨门禄,太阳权,文曲科,文昌忌\n│ │ │ ├2022年[壬寅](37虚岁)\n│ │ │ │ ├命宫干支:庚寅\n│ │ │ │ └流年四化:天梁禄,紫微权,左辅科,武曲忌\n│ │ │ ├2023年[癸卯](38虚岁)\n│ │ │ │ ├命宫干支:辛卯\n│ │ │ │ └流年四化:破军禄,巨门权,太阴科,贪狼忌\n│ │ │ ├2024年[甲辰](39虚岁)\n│ │ │ │ ├命宫干支:壬辰\n│ │ │ │ └流年四化:廉贞禄,破军权,武曲科,太阳忌\n│ │ │ ├2025年[乙巳](40虚岁)\n│ │ │ │ ├命宫干支:癸巳\n│ │ │ │ └流年四化:天机禄,天梁权,紫微科,太阴忌\n│ │ │ ├2026年[丙午](41虚岁)\n│ │ │ │ ├命宫干支:甲午\n│ │ └ └ └流年四化:天同禄,天机权,文昌科,廉贞忌\n│ │\n│ ├第5大限[辛丑]\n│ │ ├起止年份:2027年(42虚岁)~2036年(51虚岁)\n│ │ ├大限四化:巨门禄,太阳权,文曲科,文昌忌\n│ │ ├流年\n│ │ │ ├2027年[丁未](42虚岁)\n│ │ │ │ ├命宫干支:乙未\n│ │ │ │ └流年四化:太阴禄,天同权,天机科,巨门忌\n│ │ │ ├2028年[戊申](43虚岁)\n│ │ │ │ ├命宫干支:丙申\n│ │ │ │ └流年四化:贪狼禄,太阴权,右弼科,天机忌\n│ │ │ ├2029年[己酉](44虚岁)\n│ │ │ │ ├命宫干支:丁酉\n│ │ │ │ └流年四化:武曲禄,贪狼权,天梁科,文曲忌\n│ │ │ ├2030年[庚戌](45虚岁)\n│ │ │ │ ├命宫干支:戊戌\n│ │ │ │ └流年四化:太阳禄,武曲权,太阴科,天同忌\n│ │ │ ├2031年[辛亥](46虚岁)\n│ │ │ │ ├命宫干支:己亥\n│ │ │ │ └流年四化:巨门禄,太阳权,文曲科,文昌忌\n│ │ │ ├2032年[壬子](47虚岁)\n│ │ │ │ ├命宫干支:庚子\n│ │ │ │ └流年四化:天梁禄,紫微权,左辅科,武曲忌\n│ │ │ ├2033年[癸丑](48虚岁)\n│ │ │ │ ├命宫干支:辛丑\n│ │ │ │ └流年四化:破军禄,巨门权,太阴科,贪狼忌\n│ │ │ ├2034年[甲寅](49虚岁)\n│ │ │ │ ├命宫干支:庚寅\n│ │ │ │ └流年四化:廉贞禄,破军权,武曲科,太阳忌\n│ │ │ ├2035年[乙卯](50虚岁)\n│ │ │ │ ├命宫干支:辛卯\n│ │ │ │ └流年四化:天机禄,天梁权,紫微科,太阴忌\n│ │ │ ├2036年[丙辰](51虚岁)\n│ │ │ │ ├命宫干支:壬辰\n│ │ └ └ └流年四化:天同禄,天机权,文昌科,廉贞忌\n│ │\n│ ├第6大限[庚子]\n│ │ ├起止年份:2037年(52虚岁)~2046年(61虚岁)\n│ │ ├大限四化:太阳禄,武曲权,太阴科,天同忌\n│ │ ├流年\n│ │ │ ├2037年[丁巳](52虚岁)\n│ │ │ │ ├命宫干支:癸巳\n│ │ │ │ └流年四化:太阴禄,天同权,天机科,巨门忌\n│ │ │ ├2038年[戊午](53虚岁)\n│ │ │ │ ├命宫干支:甲午\n│ │ │ │ └流年四化:贪狼禄,太阴权,右弼科,天机忌\n│ │ │ ├2039年[己未](54虚岁)\n│ │ │ │ ├命宫干支:乙未\n│ │ │ │ └流年四化:武曲禄,贪狼权,天梁科,文曲忌\n│ │ │ ├2040年[庚申](55虚岁)\n│ │ │ │ ├命宫干支:丙申\n│ │ │ │ └流年四化:太阳禄,武曲权,太阴科,天同忌\n│ │ │ ├2041年[辛酉](56虚岁)\n│ │ │ │ ├命宫干支:丁酉\n│ │ │ │ └流年四化:巨门禄,太阳权,文曲科,文昌忌\n│ │ │ ├2042年[壬戌](57虚岁)\n│ │ │ │ ├命宫干支:戊戌\n│ │ │ │ └流年四化:天梁禄,紫微权,左辅科,武曲忌\n│ │ │ ├2043年[癸亥](58虚岁)\n│ │ │ │ ├命宫干支:己亥\n│ │ │ │ └流年四化:破军禄,巨门权,太阴科,贪狼忌\n│ │ │ ├2044年[甲子](59虚岁)\n│ │ │ │ ├命宫干支:庚子\n│ │ │ │ └流年四化:廉贞禄,破军权,武曲科,太阳忌\n│ │ │ ├2045年[乙丑](60虚岁)\n│ │ │ │ ├命宫干支:辛丑\n│ │ │ │ └流年四化:天机禄,天梁权,紫微科,太阴忌\n│ │ │ ├2046年[丙寅](61虚岁)\n│ │ │ │ ├命宫干支:庚寅\n│ │ └ └ └流年四化:天同禄,天机权,文昌科,廉贞忌\n│ │\n│ ├第7大限[己亥]\n│ │ ├起止年份:2047年(62虚岁)~2056年(71虚岁)\n│ │ ├大限四化:武曲禄,贪狼权,天梁科,文曲忌\n│ │ ├流年\n│ │ │ ├2047年[丁卯](62虚岁)\n│ │ │ │ ├命宫干支:辛卯\n│ │ │ │ └流年四化:太阴禄,天同权,天机科,巨门忌\n│ │ │ ├2048年[戊辰](63虚岁)\n│ │ │ │ ├命宫干支:壬辰\n│ │ │ │ └流年四化:贪狼禄,太阴权,右弼科,天机忌\n│ │ │ ├2049年[己巳](64虚岁)\n│ │ │ │ ├命宫干支:癸巳\n│ │ │ │ └流年四化:武曲禄,贪狼权,天梁科,文曲忌\n│ │ │ ├2050年[庚午](65虚岁)\n│ │ │ │ ├命宫干支:甲午\n│ │ │ │ └流年四化:太阳禄,武曲权,太阴科,天同忌\n│ │ │ ├2051年[辛未](66虚岁)\n│ │ │ │ ├命宫干支:乙未\n│ │ │ │ └流年四化:巨门禄,太阳权,文曲科,文昌忌\n│ │ │ ├2052年[壬申](67虚岁)\n│ │ │ │ ├命宫干支:丙申\n│ │ │ │ └流年四化:天梁禄,紫微权,左辅科,武曲忌\n│ │ │ ├2053年[癸酉](68虚岁)\n│ │ │ │ ├命宫干支:丁酉\n│ │ │ │ └流年四化:破军禄,巨门权,太阴科,贪狼忌\n│ │ │ ├2054年[甲戌](69虚岁)\n│ │ │ │ ├命宫干支:戊戌\n│ │ │ │ └流年四化:廉贞禄,破军权,武曲科,太阳忌\n│ │ │ ├2055年[乙亥](70虚岁)\n│ │ │ │ ├命宫干支:己亥\n│ │ │ │ └流年四化:天机禄,天梁权,紫微科,太阴忌\n│ │ │ ├2056年[丙子](71虚岁)\n│ │ │ │ ├命宫干支:庚子\n│ │ └ └ └流年四化:天同禄,天机权,文昌科,廉贞忌\n│ │\n│ ├第8大限[戊戌]\n│ │ ├起止年份:2057年(72虚岁)~2066年(81虚岁)\n│ │ ├大限四化:贪狼禄,太阴权,右弼科,天机忌\n│ │ ├流年\n│ │ │ ├2057年[丁丑](72虚岁)\n│ │ │ │ ├命宫干支:辛丑\n│ │ │ │ └流年四化:太阴禄,天同权,天机科,巨门忌\n│ │ │ ├2058年[戊寅](73虚岁)\n│ │ │ │ ├命宫干支:庚寅\n│ │ │ │ └流年四化:贪狼禄,太阴权,右弼科,天机忌\n│ │ │ ├2059年[己卯](74虚岁)\n│ │ │ │ ├命宫干支:辛卯\n│ │ │ │ └流年四化:武曲禄,贪狼权,天梁科,文曲忌\n│ │ │ ├2060年[庚辰](75虚岁)\n│ │ │ │ ├命宫干支:壬辰\n│ │ │ │ └流年四化:太阳禄,武曲权,太阴科,天同忌\n│ │ │ ├2061年[辛巳](76虚岁)\n│ │ │ │ ├命宫干支:癸巳\n│ │ │ │ └流年四化:巨门禄,太阳权,文曲科,文昌忌\n│ │ │ ├2062年[壬午](77虚岁)\n│ │ │ │ ├命宫干支:甲午\n│ │ │ │ └流年四化:天梁禄,紫微权,左辅科,武曲忌\n│ │ │ ├2063年[癸未](78虚岁)\n│ │ │ │ ├命宫干支:乙未\n│ │ │ │ └流年四化:破军禄,巨门权,太阴科,贪狼忌\n│ │ │ ├2064年[甲申](79虚岁)\n│ │ │ │ ├命宫干支:丙申\n│ │ │ │ └流年四化:廉贞禄,破军权,武曲科,太阳忌\n│ │ │ ├2065年[乙酉](80虚岁)\n│ │ │ │ ├命宫干支:丁酉\n│ │ │ │ └流年四化:天机禄,天梁权,紫微科,太阴忌\n│ │ │ ├2066年[丙戌](81虚岁)\n│ │ │ │ ├命宫干支:戊戌\n│ │ └ └ └流年四化:天同禄,天机权,文昌科,廉贞忌\n│ │\n│ ├第9大限[丁酉]\n│ │ ├起止年份:2067年(82虚岁)~2076年(91虚岁)\n│ │ ├大限四化:太阴禄,天同权,天机科,巨门忌\n│ │ ├流年\n│ │ │ ├2067年[丁亥](82虚岁)\n│ │ │ │ ├命宫干支:己亥\n│ │ │ │ └流年四化:太阴禄,天同权,天机科,巨门忌\n│ │ │ ├2068年[戊子](83虚岁)\n│ │ │ │ ├命宫干支:庚子\n│ │ │ │ └流年四化:贪狼禄,太阴权,右弼科,天机忌\n│ │ │ ├2069年[己丑](84虚岁)\n│ │ │ │ ├命宫干支:辛丑\n│ │ │ │ └流年四化:武曲禄,贪狼权,天梁科,文曲忌\n│ │ │ ├2070年[庚寅](85虚岁)\n│ │ │ │ ├命宫干支:庚寅\n│ │ │ │ └流年四化:太阳禄,武曲权,太阴科,天同忌\n│ │ │ ├2071年[辛卯](86虚岁)\n│ │ │ │ ├命宫干支:辛卯\n│ │ │ │ └流年四化:巨门禄,太阳权,文曲科,文昌忌\n│ │ │ ├2072年[壬辰](87虚岁)\n│ │ │ │ ├命宫干支:壬辰\n│ │ │ │ └流年四化:天梁禄,紫微权,左辅科,武曲忌\n│ │ │ ├2073年[癸巳](88虚岁)\n│ │ │ │ ├命宫干支:癸巳\n│ │ │ │ └流年四化:破军禄,巨门权,太阴科,贪狼忌\n│ │ │ ├2074年[甲午](89虚岁)\n│ │ │ │ ├命宫干支:甲午\n│ │ │ │ └流年四化:廉贞禄,破军权,武曲科,太阳忌\n│ │ │ ├2075年[乙未](90虚岁)\n│ │ │ │ ├命宫干支:乙未\n│ │ │ │ └流年四化:天机禄,天梁权,紫微科,太阴忌\n│ │ │ ├2076年[丙申](91虚岁)\n│ │ │ │ ├命宫干支:丙申\n│ │ └ └ └流年四化:天同禄,天机权,文昌科,廉贞忌\n│ │\n│ ├第10大限[丙申]\n│ │ ├起止年份:2077年(92虚岁)~2086年(101虚岁)\n│ │ ├大限四化:天同禄,天机权,文昌科,廉贞忌\n│ │ ├流年\n│ │ │ ├2077年[丁酉](92虚岁)\n│ │ │ │ ├命宫干支:丁酉\n│ │ │ │ └流年四化:太阴禄,天同权,天机科,巨门忌\n│ │ │ ├2078年[戊戌](93虚岁)\n│ │ │ │ ├命宫干支:戊戌\n│ │ │ │ └流年四化:贪狼禄,太阴权,右弼科,天机忌\n│ │ │ ├2079年[己亥](94虚岁)\n│ │ │ │ ├命宫干支:己亥\n│ │ │ │ └流年四化:武曲禄,贪狼权,天梁科,文曲忌\n│ │ │ ├2080年[庚子](95虚岁)\n│ │ │ │ ├命宫干支:庚子\n│ │ │ │ └流年四化:太阳禄,武曲权,太阴科,天同忌\n│ │ │ ├2081年[辛丑](96虚岁)\n│ │ │ │ ├命宫干支:辛丑\n│ │ │ │ └流年四化:巨门禄,太阳权,文曲科,文昌忌\n│ │ │ ├2082年[壬寅](97虚岁)\n│ │ │ │ ├命宫干支:庚寅\n│ │ │ │ └流年四化:天梁禄,紫微权,左辅科,武曲忌\n│ │ │ ├2083年[癸卯](98虚岁)\n│ │ │ │ ├命宫干支:辛卯\n│ │ │ │ └流年四化:破军禄,巨门权,太阴科,贪狼忌\n│ │ │ ├2084年[甲辰](99虚岁)\n│ │ │ │ ├命宫干支:壬辰\n│ │ │ │ └流年四化:廉贞禄,破军权,武曲科,太阳忌\n│ │ │ ├2085年[乙巳](100虚岁)\n│ │ │ │ ├命宫干支:癸巳\n│ │ │ │ └流年四化:天机禄,天梁权,紫微科,太阴忌\n│ │ │ ├2086年[丙午](101虚岁)\n│ │ │ │ ├命宫干支:甲午\n│ │ └ └ └流年四化:天同禄,天机权,文昌科,廉贞忌\n│ │\n│ ├第11大限[乙未]\n│ │ ├起止年份:2087年(102虚岁)~2096年(111虚岁)\n│ │ ├大限四化:天机禄,天梁权,紫微科,太阴忌\n│ │ ├流年\n│ │ │ ├2087年[丁未](102虚岁)\n│ │ │ │ ├命宫干支:乙未\n│ │ │ │ └流年四化:太阴禄,天同权,天机科,巨门忌\n│ │ │ ├2088年[戊申](103虚岁)\n│ │ │ │ ├命宫干支:丙申\n│ │ │ │ └流年四化:贪狼禄,太阴权,右弼科,天机忌\n│ │ │ ├2089年[己酉](104虚岁)\n│ │ │ │ ├命宫干支:丁酉\n│ │ │ │ └流年四化:武曲禄,贪狼权,天梁科,文曲忌\n│ │ │ ├2090年[庚戌](105虚岁)\n│ │ │ │ ├命宫干支:戊戌\n│ │ │ │ └流年四化:太阳禄,武曲权,太阴科,天同忌\n│ │ │ ├2091年[辛亥](106虚岁)\n│ │ │ │ ├命宫干支:己亥\n│ │ │ │ └流年四化:巨门禄,太阳权,文曲科,文昌忌\n│ │ │ ├2092年[壬子](107虚岁)\n│ │ │ │ ├命宫干支:庚子\n│ │ │ │ └流年四化:天梁禄,紫微权,左辅科,武曲忌\n│ │ │ ├2093年[癸丑](108虚岁)\n│ │ │ │ ├命宫干支:辛丑\n│ │ │ │ └流年四化:破军禄,巨门权,太阴科,贪狼忌\n│ │ │ ├2094年[甲寅](109虚岁)\n│ │ │ │ ├命宫干支:庚寅\n│ │ │ │ └流年四化:廉贞禄,破军权,武曲科,太阳忌\n│ │ │ ├2095年[乙卯](110虚岁)\n│ │ │ │ ├命宫干支:辛卯\n│ │ │ │ └流年四化:天机禄,天梁权,紫微科,太阴忌\n│ │ │ ├2096年[丙辰](111虚岁)\n│ │ │ │ ├命宫干支:壬辰\n│ │ └ └ └流年四化:天同禄,天机权,文昌科,廉贞忌\n│ │\n│ ├第12大限[甲午]\n│ │ ├起止年份:2097年(112虚岁)~2106年(121虚岁)\n│ │ ├大限四化:廉贞禄,破军权,武曲科,太阳忌\n│ │ ├流年\n│ │ │ ├2097年[丁巳](112虚岁)\n│ │ │ │ ├命宫干支:癸巳\n│ │ │ │ └流年四化:太阴禄,天同权,天机科,巨门忌\n│ │ │ ├2098年[戊午](113虚岁)\n│ │ │ │ ├命宫干支:甲午\n│ │ │ │ └流年四化:贪狼禄,太阴权,右弼科,天机忌\n│ │ │ ├2099年[己未](114虚岁)\n│ │ │ │ ├命宫干支:乙未\n│ │ │ │ └流年四化:武曲禄,贪狼权,天梁科,文曲忌\n│ │ │ ├2100年[庚申](115虚岁)\n│ │ │ │ ├命宫干支:丙申\n│ │ │ │ └流年四化:太阳禄,武曲权,太阴科,天同忌\n│ │ │ ├2101年[辛酉](116虚岁)\n│ │ │ │ ├命宫干支:丁酉\n│ │ │ │ └流年四化:巨门禄,太阳权,文曲科,文昌忌\n│ │ │ ├2102年[壬戌](117虚岁)\n│ │ │ │ ├命宫干支:戊戌\n│ │ │ │ └流年四化:天梁禄,紫微权,左辅科,武曲忌\n│ │ │ ├2103年[癸亥](118虚岁)\n│ │ │ │ ├命宫干支:己亥\n│ │ │ │ └流年四化:破军禄,巨门权,太阴科,贪狼忌\n│ │ │ ├2104年[甲子](119虚岁)\n│ │ │ │ ├命宫干支:庚子\n│ │ │ │ └流年四化:廉贞禄,破军权,武曲科,太阳忌\n│ │ │ ├2105年[乙丑](120虚岁)\n│ │ │ │ ├命宫干支:辛丑\n│ │ │ │ └流年四化:天机禄,天梁权,紫微科,太阴忌\n│ │ │ ├2106年[丙寅](121虚岁)\n│ │ │ │ ├命宫干支:庚寅\n│ └ └ └ └流年四化:天同禄,天机权,文昌科,廉贞忌\n│\n└[备注: 出生地 香港]\n"
  }
}
