{
  "answer_isolation": {
    "answer_payload_present": false,
    "answer_reference_disclosed": false,
    "status": "PROGRAMMATICALLY_SCANNED"
  },
  "bazi": {
    "calendar": {
      "gender": "女",
      "lunar": "甲子年冬月十七日酉时",
      "solar": "1984-12-9 18:0",
      "true_solar": "1984-12-9 18:7"
    },
    "hidden_stems_ten_gods": {
      "day": [
        "己 食神",
        "癸 七杀",
        "辛 偏财"
      ],
      "hour": [
        "辛 偏财"
      ],
      "month": [
        "癸 七杀"
      ],
      "year": [
        "癸 七杀"
      ]
    },
    "luck": {
      "cycles": [
        {
          "nominal_age": 2,
          "pillar": "乙亥",
          "start_year": 1985
        },
        {
          "nominal_age": 12,
          "pillar": "甲戌",
          "start_year": 1995
        },
        {
          "nominal_age": 22,
          "pillar": "癸酉",
          "start_year": 2005
        },
        {
          "nominal_age": 32,
          "pillar": "壬申",
          "start_year": 2015
        },
        {
          "nominal_age": 42,
          "pillar": "辛未",
          "start_year": 2025
        },
        {
          "nominal_age": 52,
          "pillar": "庚午",
          "start_year": 2035
        },
        {
          "nominal_age": 62,
          "pillar": "己巳",
          "start_year": 2045
        },
        {
          "nominal_age": 72,
          "pillar": "戊辰",
          "start_year": 2055
        },
        {
          "nominal_age": 82,
          "pillar": "丁卯",
          "start_year": 2065
        }
      ],
      "direction": "REVERSE",
      "first_major_luck_nominal_age": 2,
      "first_major_luck_year": 1985,
      "ocr_year_candidates": [
        1984,
        1985,
        1995,
        2005,
        2015,
        2025,
        2035,
        2045,
        2055,
        2065,
        2025,
        2026,
        2027,
        2028,
        2029,
        2030,
        2031,
        2032,
        2033,
        2034
      ]
    },
    "pillars": {
      "day": "丁丑",
      "hour": "己酉",
      "month": "丙子",
      "year": "甲子"
    },
    "source_image": {
      "bytes": 384112,
      "height": 1287,
      "path": "case-bank/raw/CASE-031/bazi.png",
      "sha256": "6ec81cbeefb844e5d450d1675948abbb083cc423c9bf0a1678b4c81072a6fa8d",
      "width": 1163
    },
    "transcription_status": "DERIVED_FROM_ZIWEI_TEXT_AND_IMAGE_YEAR_BOUNDARY"
  },
  "binding": {
    "source_manifest": "sources/canonical-manifest.json",
    "training_policy": "config/training-policy.json"
  },
  "case_id": "CASE-031",
  "dataset_split": "DEVELOPMENT",
  "identity_group_id": "PERSON-219EC7E3168793E0",
  "input": {
    "body_lord": "火星",
    "body_palace_branch": "酉",
    "clock_time": "1984-12-9 18:0",
    "five_element_bureau": "火六局",
    "gender": "女",
    "life_lord": "贪狼",
    "longitude": "120.000",
    "lunar_time": "甲子年冬月十七日酉时",
    "non_solar_term_pillars": "甲子 丙子 丁丑 己酉",
    "pillars": {
      "day": "丁丑",
      "hour": "己酉",
      "month": "丙子",
      "year": "甲子"
    },
    "solar_term_pillars": "甲子 丙子 丁丑 己酉",
    "true_solar_time": "1984-12-9 18:7",
    "year_doujun": "亥"
  },
  "legacy_case_id": null,
  "quality": {
    "issues": [],
    "status": "ACCEPTED"
  },
  "questions": {
    "parsed": [
      {
        "options": [
          {
            "option_id": "A",
            "text": "勤俭顾家，知书识礼，明辨是非"
          },
          {
            "option_id": "B",
            "text": "好勇争胜，说话霸气，说胜才止"
          },
          {
            "option_id": "C",
            "text": "心多贪权，急于求成，见困难挫折而离弃"
          },
          {
            "option_id": "D",
            "text": "胆小怕事，心气压抑，欠缺当机立断心志"
          }
        ],
        "preblind_profile": {
          "atomization_required": true,
          "endpoint_tags": [
            "PERSONALITY"
          ],
          "governance_tags": [],
          "option_atom_hints": {
            "A": [
              "勤俭顾家",
              "知书识礼",
              "明辨是非"
            ],
            "B": [
              "好勇争胜",
              "说话霸气",
              "说胜才止"
            ],
            "C": [
              "心多贪权",
              "急于求成",
              "见困难挫折而离弃"
            ],
            "D": [
              "胆小怕事",
              "心气压抑",
              "欠缺当机立断心志"
            ]
          },
          "reasoning_skill_tags": [
            "TOPIC_PALACE_ROUTING",
            "NATAL_STRUCTURE",
            "EVIDENCE_WEIGHTING",
            "COUNTEREVIDENCE_REVERSAL",
            "ZIWEI_BAZI_ARBITRATION",
            "OPTION_GRANULARITY",
            "STATIC_DYNAMIC_LAYERING",
            "PALACE_TRANSFORMATION_CHAIN",
            "BAZI_STRUCTURE_THEN_TRIGGER",
            "UNCERTAINTY_CALIBRATION",
            "COMPOSITE_OPTION_ATOMIZATION"
          ],
          "source_routes": [
            "S00",
            "S01",
            "S03",
            "S04",
            "S05",
            "S06",
            "S07",
            "S08",
            "S09",
            "S11",
            "S12",
            "S13",
            "S16",
            "S17",
            "S18",
            "S19"
          ],
          "subject_tags": [
            "SELF"
          ],
          "time_scope_tags": [
            "OTHER"
          ],
          "topic_tags": [
            "PERSONALITY_APPEARANCE"
          ]
        },
        "question_id": "Q1",
        "source_question_number": "1",
        "stem": "命主的性格如何？"
      },
      {
        "options": [
          {
            "option_id": "A",
            "text": "1995"
          },
          {
            "option_id": "B",
            "text": "1997"
          },
          {
            "option_id": "C",
            "text": "2003"
          },
          {
            "option_id": "D",
            "text": "2007"
          }
        ],
        "preblind_profile": {
          "atomization_required": false,
          "endpoint_tags": [
            "BUSINESS_OUTCOME"
          ],
          "governance_tags": [],
          "option_atom_hints": {
            "A": [
              "1995"
            ],
            "B": [
              "1997"
            ],
            "C": [
              "2003"
            ],
            "D": [
              "2007"
            ]
          },
          "reasoning_skill_tags": [
            "TOPIC_PALACE_ROUTING",
            "NATAL_STRUCTURE",
            "EVIDENCE_WEIGHTING",
            "COUNTEREVIDENCE_REVERSAL",
            "ZIWEI_BAZI_ARBITRATION",
            "OPTION_GRANULARITY",
            "STATIC_DYNAMIC_LAYERING",
            "PALACE_TRANSFORMATION_CHAIN",
            "BAZI_STRUCTURE_THEN_TRIGGER",
            "UNCERTAINTY_CALIBRATION",
            "TIME_LAYER_ACTIVATION",
            "EVENT_ENDPOINT_CLOSURE",
            "REALITY_SCALE_MAPPING",
            "REGION_ERA_NORMALIZATION"
          ],
          "source_routes": [
            "S00",
            "S01",
            "S02",
            "S03",
            "S04",
            "S08",
            "S09",
            "S10",
            "S11",
            "S14",
            "S15",
            "S16",
            "S17",
            "S18",
            "S19"
          ],
          "subject_tags": [
            "SELF"
          ],
          "time_scope_tags": [
            "SPECIFIC_YEAR"
          ],
          "topic_tags": [
            "WEALTH_FINANCE",
            "MAJOR_YEAR_EVENT"
          ]
        },
        "question_id": "Q2",
        "source_question_number": "2",
        "stem": "命主祖上富有，但因父好赌，哪年破产？"
      },
      {
        "options": [
          {
            "option_id": "A",
            "text": "2003"
          },
          {
            "option_id": "B",
            "text": "2007"
          },
          {
            "option_id": "C",
            "text": "2010"
          },
          {
            "option_id": "D",
            "text": "2016"
          }
        ],
        "preblind_profile": {
          "atomization_required": false,
          "endpoint_tags": [
            "LEGAL_OUTCOME"
          ],
          "governance_tags": [],
          "option_atom_hints": {
            "A": [
              "2003"
            ],
            "B": [
              "2007"
            ],
            "C": [
              "2010"
            ],
            "D": [
              "2016"
            ]
          },
          "reasoning_skill_tags": [
            "TOPIC_PALACE_ROUTING",
            "NATAL_STRUCTURE",
            "EVIDENCE_WEIGHTING",
            "COUNTEREVIDENCE_REVERSAL",
            "ZIWEI_BAZI_ARBITRATION",
            "OPTION_GRANULARITY",
            "STATIC_DYNAMIC_LAYERING",
            "PALACE_TRANSFORMATION_CHAIN",
            "BAZI_STRUCTURE_THEN_TRIGGER",
            "UNCERTAINTY_CALIBRATION",
            "TIME_LAYER_ACTIVATION",
            "EVENT_ENDPOINT_CLOSURE"
          ],
          "source_routes": [
            "S00",
            "S01",
            "S02",
            "S03",
            "S04",
            "S08",
            "S09",
            "S10",
            "S11",
            "S14",
            "S15",
            "S16",
            "S17",
            "S18",
            "S19"
          ],
          "subject_tags": [
            "SELF"
          ],
          "time_scope_tags": [
            "SPECIFIC_YEAR"
          ],
          "topic_tags": [
            "LEGAL_CONFLICT",
            "MAJOR_YEAR_EVENT"
          ]
        },
        "question_id": "Q3",
        "source_question_number": "3",
        "stem": "命主哪年在牢狱度过几个月？"
      },
      {
        "options": [
          {
            "option_id": "A",
            "text": "2008"
          },
          {
            "option_id": "B",
            "text": "2010"
          },
          {
            "option_id": "C",
            "text": "2012"
          },
          {
            "option_id": "D",
            "text": "2014"
          }
        ],
        "preblind_profile": {
          "atomization_required": false,
          "endpoint_tags": [
            "RELATIONSHIP_STATUS",
            "MAJOR_EVENT"
          ],
          "governance_tags": [],
          "option_atom_hints": {
            "A": [
              "2008"
            ],
            "B": [
              "2010"
            ],
            "C": [
              "2012"
            ],
            "D": [
              "2014"
            ]
          },
          "reasoning_skill_tags": [
            "TOPIC_PALACE_ROUTING",
            "NATAL_STRUCTURE",
            "EVIDENCE_WEIGHTING",
            "COUNTEREVIDENCE_REVERSAL",
            "ZIWEI_BAZI_ARBITRATION",
            "OPTION_GRANULARITY",
            "STATIC_DYNAMIC_LAYERING",
            "PALACE_TRANSFORMATION_CHAIN",
            "BAZI_STRUCTURE_THEN_TRIGGER",
            "UNCERTAINTY_CALIBRATION",
            "TIME_LAYER_ACTIVATION",
            "EVENT_ENDPOINT_CLOSURE",
            "RELATIONSHIP_SEQUENCE"
          ],
          "source_routes": [
            "S00",
            "S01",
            "S03",
            "S04",
            "S08",
            "S09",
            "S10",
            "S11",
            "S14",
            "S15",
            "S16",
            "S17",
            "S18",
            "S19"
          ],
          "subject_tags": [
            "SELF"
          ],
          "time_scope_tags": [
            "SPECIFIC_YEAR"
          ],
          "topic_tags": [
            "MARRIAGE_RELATIONSHIP",
            "MAJOR_YEAR_EVENT"
          ]
        },
        "question_id": "Q4",
        "source_question_number": "4",
        "stem": "命主于2005年拍拖，于何年结婚？"
      },
      {
        "options": [
          {
            "option_id": "A",
            "text": "夫妻恩爱，而且一心一意，夫妻同心照顾孩子"
          },
          {
            "option_id": "B",
            "text": "丈夫外有情人，但家用充足，命主在家照顾孩子，后离婚"
          },
          {
            "option_id": "C",
            "text": "丈夫不给家用更有情人，命主只好打工照顾孩子，后离婚"
          },
          {
            "option_id": "D",
            "text": "丈夫生意失败而离家出走，只好打工帮丈夫还债及照顾孩子"
          }
        ],
        "preblind_profile": {
          "atomization_required": true,
          "endpoint_tags": [
            "RELATIONSHIP_STATUS",
            "RELATIONSHIP_QUALITY",
            "DIVORCE",
            "BUSINESS_OUTCOME"
          ],
          "governance_tags": [],
          "option_atom_hints": {
            "A": [
              "夫妻恩爱",
              "一心一意",
              "夫妻同心照顾孩子"
            ],
            "B": [
              "丈夫外有情人",
              "家用充足",
              "命主在家照顾孩子",
              "后离婚"
            ],
            "C": [
              "丈夫不给家用更有情人",
              "命主只好打工照顾孩子",
              "后离婚"
            ],
            "D": [
              "丈夫生意失败而离家出走",
              "只好打工帮丈夫还债及照顾孩子"
            ]
          },
          "reasoning_skill_tags": [
            "TOPIC_PALACE_ROUTING",
            "NATAL_STRUCTURE",
            "EVIDENCE_WEIGHTING",
            "COUNTEREVIDENCE_REVERSAL",
            "ZIWEI_BAZI_ARBITRATION",
            "OPTION_GRANULARITY",
            "STATIC_DYNAMIC_LAYERING",
            "PALACE_TRANSFORMATION_CHAIN",
            "BAZI_STRUCTURE_THEN_TRIGGER",
            "UNCERTAINTY_CALIBRATION",
            "SUBJECT_ENTITY_ROUTING",
            "CAUSAL_ACTOR_DIRECTION",
            "COMPOSITE_OPTION_ATOMIZATION",
            "REALITY_SCALE_MAPPING",
            "REGION_ERA_NORMALIZATION",
            "CAREER_PROFILE_CLOSURE",
            "RELATIONSHIP_SEQUENCE"
          ],
          "source_routes": [
            "S00",
            "S01",
            "S02",
            "S03",
            "S04",
            "S08",
            "S09",
            "S11",
            "S16",
            "S17",
            "S18",
            "S19"
          ],
          "subject_tags": [
            "SPOUSE_PARTNER",
            "CHILDREN"
          ],
          "time_scope_tags": [
            "OTHER"
          ],
          "topic_tags": [
            "MARRIAGE_RELATIONSHIP",
            "CHILDREN_FERTILITY",
            "CAREER_EDUCATION"
          ]
        },
        "question_id": "Q5",
        "source_question_number": "5",
        "stem": "命主的感情生活情况如何？"
      }
    ],
    "question_count": 5,
    "source_path": "case-bank/raw/CASE-031/questions.txt",
    "source_sha256": "928cf76b90230e68a80581b5006918859699ba640842808299e0795f24f04bd7"
  },
  "schema": "FORTUNE-CASE-BANK-CASE-V1",
  "source_label": "例题31",
  "ziwei": {
    "sha256": "70546b6f698c96a00fd0f7664af55ed5d986a21c7ba346a069c88de7737bf67d",
    "source_path": "case-bank/raw/CASE-031/ziwei.txt",
    "text": "├符号定义\n│ ├(↓:离心自化)\n│ ├(↑:向心自化，从对宫化入)\n│ ├(┏ : 生日前小限)\n│ └( ┓: 生日后小限)\n│\n├基本信息\n│ │\n│ ├性别 : 女\n│ ├地理经度 : 120.000\n│ ├钟表时间 : 1984-12-9 18:0\n│ ├真太阳时 : 1984-12-9 18:7\n│ ├农历时间 : 甲子年冬月十七日酉时\n│ ├节气四柱 : 甲子 丙子 丁丑 己酉\n│ ├非节气四柱 : 甲子 丙子 丁丑 己酉\n│ ├五行局数 : 火六局\n│ └身主:火星; 命主:贪狼; 子年斗君:亥; 身宫:酉\n│\n├命盘十二宫\n│ │ \n│ ├子女宫[丙子]\n│ │ ├主星 : 太阳[陷][生年忌][↑禄]\n│ │ ├辅星 : 右弼[庙]\n│ │ ├小星 : 无\n│ │ ├神煞\n│ │ │ ├岁前星 : 岁建\n│ │ │ ├将前星 : 將星\n│ │ │ ├十二长生 : 冠带\n│ │ │ └太岁煞禄 : 青龙\n│ │ ├大限 : 36 ~ 45虚岁\n│ │ ├小限 : 11,23,35,47,59虚岁\n│ │ ├流年 : 1,13,25,37,49虚岁\n│ │ └限流叠宫 : 无\n│ │ \n│ ├夫妻宫[丁丑]\n│ │ ├主星 : 天府[庙]\n│ │ ├辅星 : 文昌[庙][↑忌],文曲[庙][↑科],天魁[旺],陀罗[庙]\n│ │ ├小星 : 天空[平]\n│ │ ├神煞\n│ │ │ ├岁前星 : 晦气\n│ │ │ ├将前星 : 攀鞍\n│ │ │ ├十二长生 : 沐浴\n│ │ │ └太岁煞禄 : 力士\n│ │ ├大限 : 26 ~ 35虚岁\n│ │ ├小限 : 10,22,34,46,58虚岁\n│ │ ├流年 : 2,14,26,38,50虚岁\n│ │ └限流叠宫 : 无\n│ │ \n│ ├兄弟宫[丙寅]\n│ │ ├主星 : 天机[得][↓权],太阴[旺]\n│ │ ├辅星 : 左辅[庙][↑科],禄存[庙],地空[陷],天马[旺]\n│ │ ├小星 : 天巫,孤辰[平]\n│ │ ├神煞\n│ │ │ ├岁前星 : 丧门\n│ │ │ ├将前星 : 岁驿\n│ │ │ ├十二长生 : 长生\n│ │ │ └太岁煞禄 : 博士\n│ │ ├大限 : 16 ~ 25虚岁\n│ │ ├小限 : 9,21,33,45,57虚岁\n│ │ ├流年 : 3,15,27,39,51虚岁\n│ │ └限流叠宫 : 无\n│ │ \n│ ├命  宫[丁卯]\n│ │ ├主星 : 紫微[旺],贪狼[利][↑忌]\n│ │ ├辅星 : 擎羊[陷]\n│ │ ├小星 : 红鸾[庙],天才[旺],台辅\n│ │ ├神煞\n│ │ │ ├岁前星 : 贯索\n│ │ │ ├将前星 : 息神\n│ │ │ ├十二长生 : 养\n│ │ │ └太岁煞禄 : 官符\n│ │ ├大限 : 6 ~ 15虚岁\n│ │ ├小限 : 8,20,32,44,56虚岁\n│ │ ├流年 : 4,16,28,40,52虚岁\n│ │ └限流叠宫 : 无\n│ │ \n│ ├父母宫[戊辰]\n│ │ ├主星 : 巨门[陷]\n│ │ ├辅星 : 无\n│ │ ├小星 : 恩光[庙],天贵[旺],龙池[庙],华盖[庙]\n│ │ ├神煞\n│ │ │ ├岁前星 : 官符\n│ │ │ ├将前星 : 华盖\n│ │ │ ├十二长生 : 胎\n│ │ │ └太岁煞禄 : 伏兵\n│ │ ├大限 : 116 ~ 125虚岁\n│ │ ├小限 : 7,19,31,43,55虚岁\n│ │ ├流年 : 5,17,29,41,53虚岁\n│ │ └限流叠宫 : 无\n│ │ \n│ ├福德宫[己巳]\n│ │ ├主星 : 天相[得]\n│ │ ├辅星 : 无\n│ │ ├小星 : 天厨,破碎[陷],劫煞,月德\n│ │ ├神煞\n│ │ │ ├岁前星 : 小耗\n│ │ │ ├将前星 : 劫煞\n│ │ │ ├十二长生 : 绝\n│ │ │ └太岁煞禄 : 大耗\n│ │ ├大限 : 106 ~ 115虚岁\n│ │ ├小限 : 6,18,30,42,54虚岁\n│ │ ├流年 : 6,18,30,42,54虚岁\n│ │ └限流叠宫 : 无\n│ │ \n│ ├田宅宫[庚午]\n│ │ ├主星 : 天梁[庙]\n│ │ ├辅星 : 无\n│ │ ├小星 : 三台[旺],解神[庙],天哭[陷],天虚[平],阴煞\n│ │ ├神煞\n│ │ │ ├岁前星 : 岁破\n│ │ │ ├将前星 : 灾煞\n│ │ │ ├十二长生 : 墓\n│ │ │ └太岁煞禄 : 病符\n│ │ ├大限 : 96 ~ 105虚岁\n│ │ ├小限 : 5,17,29,41,53虚岁\n│ │ ├流年 : 7,19,31,43,55虚岁\n│ │ └限流叠宫 : 无\n│ │ \n│ ├官禄宫[辛未]\n│ │ ├主星 : 廉贞[利][生年禄],七杀[庙]\n│ │ ├辅星 : 天钺[旺],铃星[利]\n│ │ ├小星 : 天刑[陷],天官[庙],大耗[平],龙德\n│ │ ├神煞\n│ │ │ ├岁前星 : 龙德\n│ │ │ ├将前星 : 天煞\n│ │ │ ├十二长生 : 死\n│ │ │ └太岁煞禄 : 喜神\n│ │ ├大限 : 86 ~ 95虚岁\n│ │ ├小限 : 4,16,28,40,52虚岁\n│ │ ├流年 : 8,20,32,44,56虚岁\n│ │ └限流叠宫 : 无\n│ │ \n│ ├交友宫[壬申]\n│ │ ├主星 : 无\n│ │ ├辅星 : 地劫[庙]\n│ │ ├小星 : 八座[庙],天使[平],截空[庙],蜚廉\n│ │ ├神煞\n│ │ │ ├岁前星 : 白虎\n│ │ │ ├将前星 : 指背\n│ │ │ ├十二长生 : 病\n│ │ │ └太岁煞禄 : 飞廉\n│ │ ├大限 : 76 ~ 85虚岁\n│ │ ├小限 : 3,15,27,39,51虚岁\n│ │ ├流年 : 9,21,33,45,57虚岁\n│ │ └限流叠宫 : 无\n│ │ \n│ ├迁移宫[癸酉][身宫]\n│ │ ├主星 : 无\n│ │ ├辅星 : 无\n│ │ ├小星 : 天喜[庙],天寿[平],天福[庙],副截[庙],咸池[平],天德[不]\n│ │ ├神煞\n│ │ │ ├岁前星 : 天德\n│ │ │ ├将前星 : 咸池\n│ │ │ ├十二长生 : 衰\n│ │ │ └太岁煞禄 : 奏书\n│ │ ├大限 : 66 ~ 75虚岁\n│ │ ├小限 : 2,14,26,38,50虚岁\n│ │ ├流年 : 10,22,34,46,58虚岁\n│ │ └限流叠宫 : 无\n│ │ \n│ ├疾厄宫[甲戌][来因]\n│ │ ├主星 : 天同[平]\n│ │ ├辅星 : 无\n│ │ ├小星 : 凤阁[庙],天伤[平],天月,旬空[陷],寡宿[陷],年解[庙]\n│ │ ├神煞\n│ │ │ ├岁前星 : 吊客\n│ │ │ ├将前星 : 月煞\n│ │ │ ├十二长生 : 帝旺\n│ │ │ └太岁煞禄 : 将军\n│ │ ├大限 : 56 ~ 65虚岁\n│ │ ├小限 : 1,13,25,37,49虚岁\n│ │ ├流年 : 11,23,35,47,59虚岁\n│ │ └限流叠宫 : 无\n│ │ \n│ └财帛宫[乙亥]\n│ │ ├主星 : 武曲[平][生年科][↑禄],破军[平][生年权]\n│ │ ├辅星 : 火星[利]\n│ │ ├小星 : 天姚[陷],封诰,副旬[平]\n│ │ ├神煞\n│ │ │ ├岁前星 : 病符\n│ │ │ ├将前星 : 亡神\n│ │ │ ├十二长生 : 临官\n│ │ │ └太岁煞禄 : 小耗\n│ │ ├大限 : 46 ~ 55虚岁\n│ │ ├小限 : 12,24,36,48,60虚岁\n│ │ ├流年 : 12,24,36,48,60虚岁\n│ │ └限流叠宫 : 无\n│\n├大限流年信息\n│ │\n│ ├第1大限[丁卯]\n│ │ ├起止年份:1989年(6虚岁)~1998年(15虚岁)\n│ │ ├大限四化:太阴禄,天同权,天机科,巨门忌\n│ │ ├流年\n│ │ │ ├1989年[己巳](6虚岁)\n│ │ │ │ ├命宫干支:己巳\n│ │ │ │ └流年四化:武曲禄,贪狼权,天梁科,文曲忌\n│ │ │ ├1990年[庚午](7虚岁)\n│ │ │ │ ├命宫干支:庚午\n│ │ │ │ └流年四化:太阳禄,武曲权,太阴科,天同忌\n│ │ │ ├1991年[辛未](8虚岁)\n│ │ │ │ ├命宫干支:辛未\n│ │ │ │ └流年四化:巨门禄,太阳权,文曲科,文昌忌\n│ │ │ ├1992年[壬申](9虚岁)\n│ │ │ │ ├命宫干支:壬申\n│ │ │ │ └流年四化:天梁禄,紫微权,左辅科,武曲忌\n│ │ │ ├1993年[癸酉](10虚岁)\n│ │ │ │ ├命宫干支:癸酉\n│ │ │ │ └流年四化:破军禄,巨门权,太阴科,贪狼忌\n│ │ │ ├1994年[甲戌](11虚岁)\n│ │ │ │ ├命宫干支:甲戌\n│ │ │ │ └流年四化:廉贞禄,破军权,武曲科,太阳忌\n│ │ │ ├1995年[乙亥](12虚岁)\n│ │ │ │ ├命宫干支:乙亥\n│ │ │ │ └流年四化:天机禄,天梁权,紫微科,太阴忌\n│ │ │ ├1996年[丙子](13虚岁)\n│ │ │ │ ├命宫干支:丙子\n│ │ │ │ └流年四化:天同禄,天机权,文昌科,廉贞忌\n│ │ │ ├1997年[丁丑](14虚岁)\n│ │ │ │ ├命宫干支:丁丑\n│ │ │ │ └流年四化:太阴禄,天同权,天机科,巨门忌\n│ │ │ ├1998年[戊寅](15虚岁)\n│ │ │ │ ├命宫干支:丙寅\n│ │ └ └ └流年四化:贪狼禄,太阴权,右弼科,天机忌\n│ │\n│ ├第2大限[丙寅]\n│ │ ├起止年份:1999年(16虚岁)~2008年(25虚岁)\n│ │ ├大限四化:天同禄,天机权,文昌科,廉贞忌\n│ │ ├流年\n│ │ │ ├1999年[己卯](16虚岁)\n│ │ │ │ ├命宫干支:丁卯\n│ │ │ │ └流年四化:武曲禄,贪狼权,天梁科,文曲忌\n│ │ │ ├2000年[庚辰](17虚岁)\n│ │ │ │ ├命宫干支:戊辰\n│ │ │ │ └流年四化:太阳禄,武曲权,太阴科,天同忌\n│ │ │ ├2001年[辛巳](18虚岁)\n│ │ │ │ ├命宫干支:己巳\n│ │ │ │ └流年四化:巨门禄,太阳权,文曲科,文昌忌\n│ │ │ ├2002年[壬午](19虚岁)\n│ │ │ │ ├命宫干支:庚午\n│ │ │ │ └流年四化:天梁禄,紫微权,左辅科,武曲忌\n│ │ │ ├2003年[癸未](20虚岁)\n│ │ │ │ ├命宫干支:辛未\n│ │ │ │ └流年四化:破军禄,巨门权,太阴科,贪狼忌\n│ │ │ ├2004年[甲申](21虚岁)\n│ │ │ │ ├命宫干支:壬申\n│ │ │ │ └流年四化:廉贞禄,破军权,武曲科,太阳忌\n│ │ │ ├2005年[乙酉](22虚岁)\n│ │ │ │ ├命宫干支:癸酉\n│ │ │ │ └流年四化:天机禄,天梁权,紫微科,太阴忌\n│ │ │ ├2006年[丙戌](23虚岁)\n│ │ │ │ ├命宫干支:甲戌\n│ │ │ │ └流年四化:天同禄,天机权,文昌科,廉贞忌\n│ │ │ ├2007年[丁亥](24虚岁)\n│ │ │ │ ├命宫干支:乙亥\n│ │ │ │ └流年四化:太阴禄,天同权,天机科,巨门忌\n│ │ │ ├2008年[戊子](25虚岁)\n│ │ │ │ ├命宫干支:丙子\n│ │ └ └ └流年四化:贪狼禄,太阴权,右弼科,天机忌\n│ │\n│ ├第3大限[丁丑]\n│ │ ├起止年份:2009年(26虚岁)~2018年(35虚岁)\n│ │ ├大限四化:太阴禄,天同权,天机科,巨门忌\n│ │ ├流年\n│ │ │ ├2009年[己丑](26虚岁)\n│ │ │ │ ├命宫干支:丁丑\n│ │ │ │ └流年四化:武曲禄,贪狼权,天梁科,文曲忌\n│ │ │ ├2010年[庚寅](27虚岁)\n│ │ │ │ ├命宫干支:丙寅\n│ │ │ │ └流年四化:太阳禄,武曲权,太阴科,天同忌\n│ │ │ ├2011年[辛卯](28虚岁)\n│ │ │ │ ├命宫干支:丁卯\n│ │ │ │ └流年四化:巨门禄,太阳权,文曲科,文昌忌\n│ │ │ ├2012年[壬辰](29虚岁)\n│ │ │ │ ├命宫干支:戊辰\n│ │ │ │ └流年四化:天梁禄,紫微权,左辅科,武曲忌\n│ │ │ ├2013年[癸巳](30虚岁)\n│ │ │ │ ├命宫干支:己巳\n│ │ │ │ └流年四化:破军禄,巨门权,太阴科,贪狼忌\n│ │ │ ├2014年[甲午](31虚岁)\n│ │ │ │ ├命宫干支:庚午\n│ │ │ │ └流年四化:廉贞禄,破军权,武曲科,太阳忌\n│ │ │ ├2015年[乙未](32虚岁)\n│ │ │ │ ├命宫干支:辛未\n│ │ │ │ └流年四化:天机禄,天梁权,紫微科,太阴忌\n│ │ │ ├2016年[丙申](33虚岁)\n│ │ │ │ ├命宫干支:壬申\n│ │ │ │ └流年四化:天同禄,天机权,文昌科,廉贞忌\n│ │ │ ├2017年[丁酉](34虚岁)\n│ │ │ │ ├命宫干支:癸酉\n│ │ │ │ └流年四化:太阴禄,天同权,天机科,巨门忌\n│ │ │ ├2018年[戊戌](35虚岁)\n│ │ │ │ ├命宫干支:甲戌\n│ │ └ └ └流年四化:贪狼禄,太阴权,右弼科,天机忌\n│ │\n│ ├第4大限[丙子]\n│ │ ├起止年份:2019年(36虚岁)~2028年(45虚岁)\n│ │ ├大限四化:天同禄,天机权,文昌科,廉贞忌\n│ │ ├流年\n│ │ │ ├2019年[己亥](36虚岁)\n│ │ │ │ ├命宫干支:乙亥\n│ │ │ │ └流年四化:武曲禄,贪狼权,天梁科,文曲忌\n│ │ │ ├2020年[庚子](37虚岁)\n│ │ │ │ ├命宫干支:丙子\n│ │ │ │ └流年四化:太阳禄,武曲权,太阴科,天同忌\n│ │ │ ├2021年[辛丑](38虚岁)\n│ │ │ │ ├命宫干支:丁丑\n│ │ │ │ └流年四化:巨门禄,太阳权,文曲科,文昌忌\n│ │ │ ├2022年[壬寅](39虚岁)\n│ │ │ │ ├命宫干支:丙寅\n│ │ │ │ └流年四化:天梁禄,紫微权,左辅科,武曲忌\n│ │ │ ├2023年[癸卯](40虚岁)\n│ │ │ │ ├命宫干支:丁卯\n│ │ │ │ └流年四化:破军禄,巨门权,太阴科,贪狼忌\n│ │ │ ├2024年[甲辰](41虚岁)\n│ │ │ │ ├命宫干支:戊辰\n│ │ │ │ └流年四化:廉贞禄,破军权,武曲科,太阳忌\n│ │ │ ├2025年[乙巳](42虚岁)\n│ │ │ │ ├命宫干支:己巳\n│ │ │ │ └流年四化:天机禄,天梁权,紫微科,太阴忌\n│ │ │ ├2026年[丙午](43虚岁)\n│ │ │ │ ├命宫干支:庚午\n│ │ │ │ └流年四化:天同禄,天机权,文昌科,廉贞忌\n│ │ │ ├2027年[丁未](44虚岁)\n│ │ │ │ ├命宫干支:辛未\n│ │ │ │ └流年四化:太阴禄,天同权,天机科,巨门忌\n│ │ │ ├2028年[戊申](45虚岁)\n│ │ │ │ ├命宫干支:壬申\n│ │ └ └ └流年四化:贪狼禄,太阴权,右弼科,天机忌\n│ │\n│ ├第5大限[乙亥]\n│ │ ├起止年份:2029年(46虚岁)~2038年(55虚岁)\n│ │ ├大限四化:天机禄,天梁权,紫微科,太阴忌\n│ │ ├流年\n│ │ │ ├2029年[己酉](46虚岁)\n│ │ │ │ ├命宫干支:癸酉\n│ │ │ │ └流年四化:武曲禄,贪狼权,天梁科,文曲忌\n│ │ │ ├2030年[庚戌](47虚岁)\n│ │ │ │ ├命宫干支:甲戌\n│ │ │ │ └流年四化:太阳禄,武曲权,太阴科,天同忌\n│ │ │ ├2031年[辛亥](48虚岁)\n│ │ │ │ ├命宫干支:乙亥\n│ │ │ │ └流年四化:巨门禄,太阳权,文曲科,文昌忌\n│ │ │ ├2032年[壬子](49虚岁)\n│ │ │ │ ├命宫干支:丙子\n│ │ │ │ └流年四化:天梁禄,紫微权,左辅科,武曲忌\n│ │ │ ├2033年[癸丑](50虚岁)\n│ │ │ │ ├命宫干支:丁丑\n│ │ │ │ └流年四化:破军禄,巨门权,太阴科,贪狼忌\n│ │ │ ├2034年[甲寅](51虚岁)\n│ │ │ │ ├命宫干支:丙寅\n│ │ │ │ └流年四化:廉贞禄,破军权,武曲科,太阳忌\n│ │ │ ├2035年[乙卯](52虚岁)\n│ │ │ │ ├命宫干支:丁卯\n│ │ │ │ └流年四化:天机禄,天梁权,紫微科,太阴忌\n│ │ │ ├2036年[丙辰](53虚岁)\n│ │ │ │ ├命宫干支:戊辰\n│ │ │ │ └流年四化:天同禄,天机权,文昌科,廉贞忌\n│ │ │ ├2037年[丁巳](54虚岁)\n│ │ │ │ ├命宫干支:己巳\n│ │ │ │ └流年四化:太阴禄,天同权,天机科,巨门忌\n│ │ │ ├2038年[戊午](55虚岁)\n│ │ │ │ ├命宫干支:庚午\n│ │ └ └ └流年四化:贪狼禄,太阴权,右弼科,天机忌\n│ │\n│ ├第6大限[甲戌]\n│ │ ├起止年份:2039年(56虚岁)~2048年(65虚岁)\n│ │ ├大限四化:廉贞禄,破军权,武曲科,太阳忌\n│ │ ├流年\n│ │ │ ├2039年[己未](56虚岁)\n│ │ │ │ ├命宫干支:辛未\n│ │ │ │ └流年四化:武曲禄,贪狼权,天梁科,文曲忌\n│ │ │ ├2040年[庚申](57虚岁)\n│ │ │ │ ├命宫干支:壬申\n│ │ │ │ └流年四化:太阳禄,武曲权,太阴科,天同忌\n│ │ │ ├2041年[辛酉](58虚岁)\n│ │ │ │ ├命宫干支:癸酉\n│ │ │ │ └流年四化:巨门禄,太阳权,文曲科,文昌忌\n│ │ │ ├2042年[壬戌](59虚岁)\n│ │ │ │ ├命宫干支:甲戌\n│ │ │ │ └流年四化:天梁禄,紫微权,左辅科,武曲忌\n│ │ │ ├2043年[癸亥](60虚岁)\n│ │ │ │ ├命宫干支:乙亥\n│ │ │ │ └流年四化:破军禄,巨门权,太阴科,贪狼忌\n│ │ │ ├2044年[甲子](61虚岁)\n│ │ │ │ ├命宫干支:丙子\n│ │ │ │ └流年四化:廉贞禄,破军权,武曲科,太阳忌\n│ │ │ ├2045年[乙丑](62虚岁)\n│ │ │ │ ├命宫干支:丁丑\n│ │ │ │ └流年四化:天机禄,天梁权,紫微科,太阴忌\n│ │ │ ├2046年[丙寅](63虚岁)\n│ │ │ │ ├命宫干支:丙寅\n│ │ │ │ └流年四化:天同禄,天机权,文昌科,廉贞忌\n│ │ │ ├2047年[丁卯](64虚岁)\n│ │ │ │ ├命宫干支:丁卯\n│ │ │ │ └流年四化:太阴禄,天同权,天机科,巨门忌\n│ │ │ ├2048年[戊辰](65虚岁)\n│ │ │ │ ├命宫干支:戊辰\n│ │ └ └ └流年四化:贪狼禄,太阴权,右弼科,天机忌\n│ │\n│ ├第7大限[癸酉]\n│ │ ├起止年份:2049年(66虚岁)~2058年(75虚岁)\n│ │ ├大限四化:破军禄,巨门权,太阴科,贪狼忌\n│ │ ├流年\n│ │ │ ├2049年[己巳](66虚岁)\n│ │ │ │ ├命宫干支:己巳\n│ │ │ │ └流年四化:武曲禄,贪狼权,天梁科,文曲忌\n│ │ │ ├2050年[庚午](67虚岁)\n│ │ │ │ ├命宫干支:庚午\n│ │ │ │ └流年四化:太阳禄,武曲权,太阴科,天同忌\n│ │ │ ├2051年[辛未](68虚岁)\n│ │ │ │ ├命宫干支:辛未\n│ │ │ │ └流年四化:巨门禄,太阳权,文曲科,文昌忌\n│ │ │ ├2052年[壬申](69虚岁)\n│ │ │ │ ├命宫干支:壬申\n│ │ │ │ └流年四化:天梁禄,紫微权,左辅科,武曲忌\n│ │ │ ├2053年[癸酉](70虚岁)\n│ │ │ │ ├命宫干支:癸酉\n│ │ │ │ └流年四化:破军禄,巨门权,太阴科,贪狼忌\n│ │ │ ├2054年[甲戌](71虚岁)\n│ │ │ │ ├命宫干支:甲戌\n│ │ │ │ └流年四化:廉贞禄,破军权,武曲科,太阳忌\n│ │ │ ├2055年[乙亥](72虚岁)\n│ │ │ │ ├命宫干支:乙亥\n│ │ │ │ └流年四化:天机禄,天梁权,紫微科,太阴忌\n│ │ │ ├2056年[丙子](73虚岁)\n│ │ │ │ ├命宫干支:丙子\n│ │ │ │ └流年四化:天同禄,天机权,文昌科,廉贞忌\n│ │ │ ├2057年[丁丑](74虚岁)\n│ │ │ │ ├命宫干支:丁丑\n│ │ │ │ └流年四化:太阴禄,天同权,天机科,巨门忌\n│ │ │ ├2058年[戊寅](75虚岁)\n│ │ │ │ ├命宫干支:丙寅\n│ │ └ └ └流年四化:贪狼禄,太阴权,右弼科,天机忌\n│ │\n│ ├第8大限[壬申]\n│ │ ├起止年份:2059年(76虚岁)~2068年(85虚岁)\n│ │ ├大限四化:天梁禄,紫微权,左辅科,武曲忌\n│ │ ├流年\n│ │ │ ├2059年[己卯](76虚岁)\n│ │ │ │ ├命宫干支:丁卯\n│ │ │ │ └流年四化:武曲禄,贪狼权,天梁科,文曲忌\n│ │ │ ├2060年[庚辰](77虚岁)\n│ │ │ │ ├命宫干支:戊辰\n│ │ │ │ └流年四化:太阳禄,武曲权,太阴科,天同忌\n│ │ │ ├2061年[辛巳](78虚岁)\n│ │ │ │ ├命宫干支:己巳\n│ │ │ │ └流年四化:巨门禄,太阳权,文曲科,文昌忌\n│ │ │ ├2062年[壬午](79虚岁)\n│ │ │ │ ├命宫干支:庚午\n│ │ │ │ └流年四化:天梁禄,紫微权,左辅科,武曲忌\n│ │ │ ├2063年[癸未](80虚岁)\n│ │ │ │ ├命宫干支:辛未\n│ │ │ │ └流年四化:破军禄,巨门权,太阴科,贪狼忌\n│ │ │ ├2064年[甲申](81虚岁)\n│ │ │ │ ├命宫干支:壬申\n│ │ │ │ └流年四化:廉贞禄,破军权,武曲科,太阳忌\n│ │ │ ├2065年[乙酉](82虚岁)\n│ │ │ │ ├命宫干支:癸酉\n│ │ │ │ └流年四化:天机禄,天梁权,紫微科,太阴忌\n│ │ │ ├2066年[丙戌](83虚岁)\n│ │ │ │ ├命宫干支:甲戌\n│ │ │ │ └流年四化:天同禄,天机权,文昌科,廉贞忌\n│ │ │ ├2067年[丁亥](84虚岁)\n│ │ │ │ ├命宫干支:乙亥\n│ │ │ │ └流年四化:太阴禄,天同权,天机科,巨门忌\n│ │ │ ├2068年[戊子](85虚岁)\n│ │ │ │ ├命宫干支:丙子\n│ │ └ └ └流年四化:贪狼禄,太阴权,右弼科,天机忌\n│ │\n│ ├第9大限[辛未]\n│ │ ├起止年份:2069年(86虚岁)~2078年(95虚岁)\n│ │ ├大限四化:巨门禄,太阳权,文曲科,文昌忌\n│ │ ├流年\n│ │ │ ├2069年[己丑](86虚岁)\n│ │ │ │ ├命宫干支:丁丑\n│ │ │ │ └流年四化:武曲禄,贪狼权,天梁科,文曲忌\n│ │ │ ├2070年[庚寅](87虚岁)\n│ │ │ │ ├命宫干支:丙寅\n│ │ │ │ └流年四化:太阳禄,武曲权,太阴科,天同忌\n│ │ │ ├2071年[辛卯](88虚岁)\n│ │ │ │ ├命宫干支:丁卯\n│ │ │ │ └流年四化:巨门禄,太阳权,文曲科,文昌忌\n│ │ │ ├2072年[壬辰](89虚岁)\n│ │ │ │ ├命宫干支:戊辰\n│ │ │ │ └流年四化:天梁禄,紫微权,左辅科,武曲忌\n│ │ │ ├2073年[癸巳](90虚岁)\n│ │ │ │ ├命宫干支:己巳\n│ │ │ │ └流年四化:破军禄,巨门权,太阴科,贪狼忌\n│ │ │ ├2074年[甲午](91虚岁)\n│ │ │ │ ├命宫干支:庚午\n│ │ │ │ └流年四化:廉贞禄,破军权,武曲科,太阳忌\n│ │ │ ├2075年[乙未](92虚岁)\n│ │ │ │ ├命宫干支:辛未\n│ │ │ │ └流年四化:天机禄,天梁权,紫微科,太阴忌\n│ │ │ ├2076年[丙申](93虚岁)\n│ │ │ │ ├命宫干支:壬申\n│ │ │ │ └流年四化:天同禄,天机权,文昌科,廉贞忌\n│ │ │ ├2077年[丁酉](94虚岁)\n│ │ │ │ ├命宫干支:癸酉\n│ │ │ │ └流年四化:太阴禄,天同权,天机科,巨门忌\n│ │ │ ├2078年[戊戌](95虚岁)\n│ │ │ │ ├命宫干支:甲戌\n│ │ └ └ └流年四化:贪狼禄,太阴权,右弼科,天机忌\n│ │\n│ ├第10大限[庚午]\n│ │ ├起止年份:2079年(96虚岁)~2088年(105虚岁)\n│ │ ├大限四化:太阳禄,武曲权,太阴科,天同忌\n│ │ ├流年\n│ │ │ ├2079年[己亥](96虚岁)\n│ │ │ │ ├命宫干支:乙亥\n│ │ │ │ └流年四化:武曲禄,贪狼权,天梁科,文曲忌\n│ │ │ ├2080年[庚子](97虚岁)\n│ │ │ │ ├命宫干支:丙子\n│ │ │ │ └流年四化:太阳禄,武曲权,太阴科,天同忌\n│ │ │ ├2081年[辛丑](98虚岁)\n│ │ │ │ ├命宫干支:丁丑\n│ │ │ │ └流年四化:巨门禄,太阳权,文曲科,文昌忌\n│ │ │ ├2082年[壬寅](99虚岁)\n│ │ │ │ ├命宫干支:丙寅\n│ │ │ │ └流年四化:天梁禄,紫微权,左辅科,武曲忌\n│ │ │ ├2083年[癸卯](100虚岁)\n│ │ │ │ ├命宫干支:丁卯\n│ │ │ │ └流年四化:破军禄,巨门权,太阴科,贪狼忌\n│ │ │ ├2084年[甲辰](101虚岁)\n│ │ │ │ ├命宫干支:戊辰\n│ │ │ │ └流年四化:廉贞禄,破军权,武曲科,太阳忌\n│ │ │ ├2085年[乙巳](102虚岁)\n│ │ │ │ ├命宫干支:己巳\n│ │ │ │ └流年四化:天机禄,天梁权,紫微科,太阴忌\n│ │ │ ├2086年[丙午](103虚岁)\n│ │ │ │ ├命宫干支:庚午\n│ │ │ │ └流年四化:天同禄,天机权,文昌科,廉贞忌\n│ │ │ ├2087年[丁未](104虚岁)\n│ │ │ │ ├命宫干支:辛未\n│ │ │ │ └流年四化:太阴禄,天同权,天机科,巨门忌\n│ │ │ ├2088年[戊申](105虚岁)\n│ │ │ │ ├命宫干支:壬申\n│ │ └ └ └流年四化:贪狼禄,太阴权,右弼科,天机忌\n│ │\n│ ├第11大限[己巳]\n│ │ ├起止年份:2089年(106虚岁)~2098年(115虚岁)\n│ │ ├大限四化:武曲禄,贪狼权,天梁科,文曲忌\n│ │ ├流年\n│ │ │ ├2089年[己酉](106虚岁)\n│ │ │ │ ├命宫干支:癸酉\n│ │ │ │ └流年四化:武曲禄,贪狼权,天梁科,文曲忌\n│ │ │ ├2090年[庚戌](107虚岁)\n│ │ │ │ ├命宫干支:甲戌\n│ │ │ │ └流年四化:太阳禄,武曲权,太阴科,天同忌\n│ │ │ ├2091年[辛亥](108虚岁)\n│ │ │ │ ├命宫干支:乙亥\n│ │ │ │ └流年四化:巨门禄,太阳权,文曲科,文昌忌\n│ │ │ ├2092年[壬子](109虚岁)\n│ │ │ │ ├命宫干支:丙子\n│ │ │ │ └流年四化:天梁禄,紫微权,左辅科,武曲忌\n│ │ │ ├2093年[癸丑](110虚岁)\n│ │ │ │ ├命宫干支:丁丑\n│ │ │ │ └流年四化:破军禄,巨门权,太阴科,贪狼忌\n│ │ │ ├2094年[甲寅](111虚岁)\n│ │ │ │ ├命宫干支:丙寅\n│ │ │ │ └流年四化:廉贞禄,破军权,武曲科,太阳忌\n│ │ │ ├2095年[乙卯](112虚岁)\n│ │ │ │ ├命宫干支:丁卯\n│ │ │ │ └流年四化:天机禄,天梁权,紫微科,太阴忌\n│ │ │ ├2096年[丙辰](113虚岁)\n│ │ │ │ ├命宫干支:戊辰\n│ │ │ │ └流年四化:天同禄,天机权,文昌科,廉贞忌\n│ │ │ ├2097年[丁巳](114虚岁)\n│ │ │ │ ├命宫干支:己巳\n│ │ │ │ └流年四化:太阴禄,天同权,天机科,巨门忌\n│ │ │ ├2098年[戊午](115虚岁)\n│ │ │ │ ├命宫干支:庚午\n│ │ └ └ └流年四化:贪狼禄,太阴权,右弼科,天机忌\n│ │\n│ ├第12大限[戊辰]\n│ │ ├起止年份:2099年(116虚岁)~2108年(125虚岁)\n│ │ ├大限四化:贪狼禄,太阴权,右弼科,天机忌\n│ │ ├流年\n│ │ │ ├2099年[己未](116虚岁)\n│ │ │ │ ├命宫干支:辛未\n│ │ │ │ └流年四化:武曲禄,贪狼权,天梁科,文曲忌\n│ │ │ ├2100年[庚申](117虚岁)\n│ │ │ │ ├命宫干支:壬申\n│ │ │ │ └流年四化:太阳禄,武曲权,太阴科,天同忌\n│ │ │ ├2101年[辛酉](118虚岁)\n│ │ │ │ ├命宫干支:癸酉\n│ │ │ │ └流年四化:巨门禄,太阳权,文曲科,文昌忌\n│ │ │ ├2102年[壬戌](119虚岁)\n│ │ │ │ ├命宫干支:甲戌\n│ │ │ │ └流年四化:天梁禄,紫微权,左辅科,武曲忌\n│ │ │ ├2103年[癸亥](120虚岁)\n│ │ │ │ ├命宫干支:乙亥\n│ │ │ │ └流年四化:破军禄,巨门权,太阴科,贪狼忌\n│ │ │ ├2104年[甲子](121虚岁)\n│ │ │ │ ├命宫干支:丙子\n│ │ │ │ └流年四化:廉贞禄,破军权,武曲科,太阳忌\n│ │ │ ├2105年[乙丑](122虚岁)\n│ │ │ │ ├命宫干支:丁丑\n│ │ │ │ └流年四化:天机禄,天梁权,紫微科,太阴忌\n│ │ │ ├2106年[丙寅](123虚岁)\n│ │ │ │ ├命宫干支:丙寅\n│ │ │ │ └流年四化:天同禄,天机权,文昌科,廉贞忌\n│ │ │ ├2107年[丁卯](124虚岁)\n│ │ │ │ ├命宫干支:丁卯\n│ │ │ │ └流年四化:太阴禄,天同权,天机科,巨门忌\n│ │ │ ├2108年[戊辰](125虚岁)\n│ │ │ │ ├命宫干支:戊辰\n│ └ └ └ └流年四化:贪狼禄,太阴权,右弼科,天机忌\n│\n└[备注: 出生地 中国香港]\n"
  }
}
